bloomr/__init__.py
bloomr/download.py
bloomr/solver.py
bloomr/visualize.py
bloomr/bin/bloomr-rust-linux-x86_64
bloomr/bin/bloomr-rust-macos-aarch64
bloomr/bin/bloomr-rust-macos-x86_64
bloomr/bin/bloomr-rust-windows-x86_64.exe
bloomr-0.1.2.dist-info/licenses/LICENSE
bloomr-0.1.2.dist-info/METADATA
bloomr-0.1.2.dist-info/WHEEL
bloomr-0.1.2.dist-info/top_level.txt
bloomr-0.1.2.dist-info/RECORD
