Metadata-Version: 2.4
Name: bloomr
Version: 0.1.2
Summary: Hybrid Blossom-Greedy approach for constructing Eulerian tours on real road graphs.
Author-email: Nathaniel Hey <gnathoi@nat.je>
License: Apache-2.0
Project-URL: Homepage, https://github.com/gnathoi/bloomr
Project-URL: Documentation, https://github.com/gnathoi/bloomr#readme
Project-URL: Repository, https://github.com/gnathoi/bloomr
Project-URL: Issues, https://github.com/gnathoi/bloomr/issues
Keywords: chinese-postman,graph-algorithms,routing,osmnx,blossom-algorithm,eulerian-circuit
Classifier: Development Status :: 3 - Alpha
Classifier: Intended Audience :: Developers
Classifier: Intended Audience :: Science/Research
Classifier: License :: OSI Approved :: Apache Software License
Classifier: Operating System :: OS Independent
Classifier: Programming Language :: Python :: 3
Classifier: Programming Language :: Python :: 3.13
Classifier: Programming Language :: Rust
Classifier: Topic :: Scientific/Engineering :: GIS
Classifier: Topic :: Software Development :: Libraries :: Python Modules
Requires-Python: >=3.9
License-File: LICENSE
Requires-Dist: osmnx>=1.9.0
Requires-Dist: networkx>=3.0
Provides-Extra: viz
Requires-Dist: matplotlib>=3.5.0; extra == "viz"
Requires-Dist: contextily>=1.3.0; extra == "viz"
Provides-Extra: dev
Requires-Dist: pytest>=7.0; extra == "dev"
Requires-Dist: black>=23.0; extra == "dev"
Requires-Dist: ruff>=0.1.0; extra == "dev"
Requires-Dist: mypy>=1.0; extra == "dev"
Dynamic: license-file
